grigodeenv2/__init__.py
grigodeenv2/environ.py
grigode_env_2-1.0.dist-info/LICENSE
grigode_env_2-1.0.dist-info/METADATA
grigode_env_2-1.0.dist-info/WHEEL
grigode_env_2-1.0.dist-info/top_level.txt
grigode_env_2-1.0.dist-info/RECORD
