Metadata-Version: 2.1
Name: grigode-env-2
Version: 1.0
Summary: grigode-env-2 is a library for reading and managing key-value pairs from .env files in your projects.
Home-page: https://github.com/angelchavez19/grigode-env-2
Author: Angel Chávez
Author-email: infoangelchavez@gmail.com
Project-URL: Bug Tracker, https://github.com/angelchavez19/grigode-env-2/issues
Classifier: Programming Language :: Python :: 3
Classifier: License :: OSI Approved :: MIT License
Classifier: Operating System :: OS Independent
License-File: LICENSE
